pism_palseries.py
pism_palseries-0.1.0.data/scripts/pism_palseries.py
pism_palseries-0.1.0.dist-info/COPYING
pism_palseries-0.1.0.dist-info/METADATA
pism_palseries-0.1.0.dist-info/WHEEL
pism_palseries-0.1.0.dist-info/top_level.txt
pism_palseries-0.1.0.dist-info/RECORD
