Metadata-Version: 2.1
Name: pism-palseries
Version: 0.1.0
Summary: Prepare scalar modifiers for the Parallel Ice Sheet Model
Home-page: http://github.com/juseg/pism-palseries
Author: Julien Seguinot
Author-email: seguinot@vaw.baug.ethz.ch
License: gpl-3.0
Platform: UNKNOWN
Requires-Dist: netCDF4
Requires-Dist: numpy
